autodoc_mcp/__init__.py
autodoc_mcp/config.py
autodoc_mcp/exceptions.py
autodoc_mcp/health.py
autodoc_mcp/main.py
autodoc_mcp/models.py
autodoc_mcp/observability.py
autodoc_mcp/security.py
autodoc_mcp/core/__init__.py
autodoc_mcp/core/cache_manager.py
autodoc_mcp/core/context_fetcher.py
autodoc_mcp/core/context_formatter.py
autodoc_mcp/core/dependency_parser.py
autodoc_mcp/core/dependency_resolver.py
autodoc_mcp/core/doc_fetcher.py
autodoc_mcp/core/error_formatter.py
autodoc_mcp/core/network_client.py
autodoc_mcp/core/network_resilience.py
autodoc_mcp/core/version_resolver.py
autodoc_mcp-0.5.1.dist-info/METADATA
autodoc_mcp-0.5.1.dist-info/WHEEL
autodoc_mcp-0.5.1.dist-info/entry_points.txt
autodoc_mcp-0.5.1.dist-info/licenses/LICENSE
autodoc_mcp-0.5.1.dist-info/RECORD
