Metadata-Version: 2.4
Name: autodoc-mcp
Version: 0.5.1
Summary: MCP server for automatic Python package documentation context
Project-URL: Homepage, https://github.com/bradleyfay/autodoc-mcp
Project-URL: Repository, https://github.com/bradleyfay/autodoc-mcp.git
Project-URL: Issues, https://github.com/bradleyfay/autodoc-mcp/issues
Author-email: AutoDocs Team <team@autodocs.dev>
License: MIT
License-File: LICENSE
Requires-Python: >=3.11
Requires-Dist: click>=8.0.0
Requires-Dist: fastmcp>=2.0.0
Requires-Dist: httpx>=0.25.0
Requires-Dist: packaging>=23.0
Requires-Dist: pydantic>=2.0.0
Requires-Dist: structlog>=23.2.0
Requires-Dist: tomlkit>=0.12.0
Provides-Extra: dev
Requires-Dist: mypy>=1.6.0; extra == 'dev'
Requires-Dist: pre-commit>=3.5.0; extra == 'dev'
Requires-Dist: pytest-asyncio>=0.21.0; extra == 'dev'
Requires-Dist: pytest-cov>=4.1.0; extra == 'dev'
Requires-Dist: pytest-httpx>=0.30.0; extra == 'dev'
Requires-Dist: pytest-mock>=3.11.0; extra == 'dev'
Requires-Dist: pytest-randomly>=3.12.0; extra == 'dev'
Requires-Dist: pytest-timeout>=2.1.0; extra == 'dev'
Requires-Dist: pytest-xdist>=3.3.0; extra == 'dev'
Requires-Dist: pytest>=7.4.0; extra == 'dev'
Requires-Dist: ruff>=0.1.0; extra == 'dev'
